pyact_engine/main.py
pyact_engine-0.1.0.dist-info/METADATA
pyact_engine-0.1.0.dist-info/WHEEL
pyact_engine-0.1.0.dist-info/entry_points.txt
pyact_engine-0.1.0.dist-info/top_level.txt
pyact_engine-0.1.0.dist-info/RECORD
