Metadata-Version: 2.4
Name: pyact-engine
Version: 0.1.0
Summary: A powerful recursive Markdown template engine
Author-email: Abstergo## <abstergo.hash@gmail.com>
License: Apache-2.0
Project-URL: Homepage, https://github.com/Abstergo2003/PyAct
Project-URL: Documentation, https://github.com/Abstergo2003/PyAct/blob/main/README.md
Project-URL: Issues, https://github.com/Abstergo2003/PyAct/issues
Classifier: Development Status :: 4 - Beta
Classifier: Intended Audience :: Developers
Classifier: Intended Audience :: Science/Research
Classifier: Intended Audience :: Education
Classifier: License :: OSI Approved :: Apache Software License
Classifier: Programming Language :: Python :: 3
Classifier: Programming Language :: Python :: 3.8
Classifier: Programming Language :: Python :: 3.9
Classifier: Programming Language :: Python :: 3.10
Classifier: Programming Language :: Python :: 3.11
Classifier: Programming Language :: Python :: 3.12
Classifier: Topic :: Scientific/Engineering
Classifier: Topic :: Software Development :: Libraries :: Python Modules
Requires-Python: >=3.7
